whisper_eval_serbian/__init__.py
whisper_eval_serbian/evaluator.py
whisper_eval_serbian/model_wrapper.py
whisper_eval_serbian/task.py
whisper_eval_serbian/utils.py
whisper_eval_serbian-0.0.35.dist-info/licenses/LICENSE
whisper_eval_serbian-0.0.35.dist-info/METADATA
whisper_eval_serbian-0.0.35.dist-info/WHEEL
whisper_eval_serbian-0.0.35.dist-info/top_level.txt
whisper_eval_serbian-0.0.35.dist-info/RECORD
