Metadata-Version: 2.4
Name: whisper-eval-serbian
Version: 0.0.35
Summary: An evaluation framework for Serbian Whisper models.
Author-email: Dejan Čugalj <dejan@textintellect.com>
Maintainer-email: Dejan Čugalj <dejan@textintellect.com>
License-Expression: Apache-2.0
Project-URL: Repository, https://github.com/DeanChugall/AiDA.git
Project-URL: Documentation, https://aida.guru/docs
Project-URL: Homepage, https://aida.guru
Keywords: TTS,ASR,Serbian,Audio,AI
Classifier: Programming Language :: Python :: 3
Classifier: Programming Language :: Python :: 3.12
Classifier: Operating System :: OS Independent
Classifier: Development Status :: 4 - Beta
Classifier: Intended Audience :: Developers
Classifier: Intended Audience :: Education
Classifier: Intended Audience :: Science/Research
Classifier: Natural Language :: Serbian
Requires-Python: <4.0,>=3.10
License-File: LICENSE
Requires-Dist: transformers>=4.55.0
Requires-Dist: datasets<4.0.0,>=3.4.1
Requires-Dist: evaluate>=0.4.5
Requires-Dist: jiwer>=4.0.0
Requires-Dist: rouge-score>=0.1.2
Requires-Dist: sacrebleu>=2.5.1
Requires-Dist: soundfile>=0.13.1
Requires-Dist: librosa>=0.11.0
Requires-Dist: tqdm>=4.67.1
Requires-Dist: cyrtranslit>=1.1.1
Provides-Extra: dev
Requires-Dist: torch>=2.7.0; extra == "dev"
Requires-Dist: loguru>=0.7.3; extra == "dev"
Requires-Dist: python-dotenv>=1.1.0; extra == "dev"
Requires-Dist: torchvision>=0.22.0; extra == "dev"
Requires-Dist: torchaudio>=2.7.0; extra == "dev"
Requires-Dist: torchmetrics>=1.8.0; extra == "dev"
Requires-Dist: pandas>=2.3.1; extra == "dev"
Requires-Dist: ruff>=0.11.10; extra == "dev"
Requires-Dist: pytest>=8.3.5; extra == "dev"
Requires-Dist: pre-commit>=4.2.0; extra == "dev"
Requires-Dist: black>=24.4.2; extra == "dev"
Requires-Dist: jupyterlab>=4.4.2; extra == "dev"
Requires-Dist: ipywidgets>=8.1.7; extra == "dev"
Requires-Dist: seaborn>=0.13.2; extra == "dev"
Dynamic: license-file
